ds100nbconvert
