Metadata-Version: 1.0
Name: ds100nbconvert
Version: 0.3
Summary: dsin100days custom nbconvert, copied from nbextensions
Home-page: UNKNOWN
Author: dinesh
Author-email: dinesh@micropyramid.com
License: LICENCE
Platform: UNKNOWN
